devqubit_qiskit/__init__.py
devqubit_qiskit/adapter.py
devqubit_qiskit/circuits.py
devqubit_qiskit/device.py
devqubit_qiskit/envelope.py
devqubit_qiskit/py.typed
devqubit_qiskit/results.py
devqubit_qiskit/serialization.py
devqubit_qiskit/utils.py
devqubit_qiskit-0.1.10.dist-info/METADATA
devqubit_qiskit-0.1.10.dist-info/WHEEL
devqubit_qiskit-0.1.10.dist-info/entry_points.txt
devqubit_qiskit-0.1.10.dist-info/licenses/LICENSE
devqubit_qiskit-0.1.10.dist-info/RECORD
